pryttier/__init__.py
pryttier/colors.py
pryttier/math.py
pryttier/tools.py
pryttier-0.2.2.dist-info/licenses/LICENSE
pryttier-0.2.2.dist-info/METADATA
pryttier-0.2.2.dist-info/WHEEL
pryttier-0.2.2.dist-info/top_level.txt
pryttier-0.2.2.dist-info/RECORD
