Metadata-Version: 2.4
Name: pryttier
Version: 0.2.2
Summary: A Python Tool Package
Author: HussuBro010 (Hussain Vohra)
Author-email: <hussainv2807@gmail.com>
Keywords: python,pretty,python-utils,python-easy,math,tools,colors
Classifier: Intended Audience :: Developers
Classifier: Programming Language :: Python :: 3
Classifier: Operating System :: Microsoft :: Windows
License-File: LICENSE
Requires-Dist: numpy
Requires-Dist: scipy
Requires-Dist: multipledispatch
Dynamic: author
Dynamic: author-email
Dynamic: classifier
Dynamic: description
Dynamic: description-content-type
Dynamic: keywords
Dynamic: license-file
Dynamic: requires-dist
Dynamic: summary
